{
  "data": [
		{
			"id": 418,
			"title": "Birajte svoja predavanja da nebi poslje bilo cile mile. <a href=\"https://t.co/xvACxGrr22\" rel=\"nofollow\">https://t.co/xvACxGrr22</a>",
			"body": null,
			"feed_name": "twitter",
			"type_name": "tweet",
			"url": "https://twitter.com/neektza/status/633640326033461248",
			"images": [],
			"created_at": "2015-08-20T13:25:11.817Z",
			"updated_at": "2015-08-20T13:25:11.817Z",
			"thread_updated_ts": 1439906600,
			"thread_updated_at": "2015-08-18T14:03:20.000Z",
			"author": {
				"id": "neektza",
				"avatar_url": "http://pbs.twimg.com/profile_images/487184555733164032/--EYb4oF_normal.jpeg"
			},
			"service_ids": [
				6
			],
			"is_approved": true,
			"is_pinned": false,
			"popularity": 0,
			"quoted_status": {
				"title": "Influence the content of <a class=\"tweet-url hashtag\" href=\"https://twitter.com/#!/search?q=%23WebCamp\" rel=\"nofollow\" title=\"#WebCamp\">#WebCamp</a> Zagreb! If you're a ticket holder go and cast a <a class=\"tweet-url hashtag\" href=\"https://twitter.com/#!/search?q=%23vote\" rel=\"nofollow\" title=\"#vote\">#vote</a> for your favourite <a class=\"tweet-url hashtag\" href=\"https://twitter.com/#!/search?q=%23talk\" rel=\"nofollow\" title=\"#talk\">#talk</a> now <a href=\"https://t.co/viluRnppKB\" rel=\"nofollow\">https://t.co/viluRnppKB</a>",
				"url": "https://twitter.com/webcampzg/status/633583744243384320",
				"created_at": "Tue Aug 18 10:18:30 +0000 2015",
				"author": {
					"id": "WebCampZg",
					"avatar_url": "http://pbs.twimg.com/profile_images/569764810296799232/bx3rm45a_normal.png"
				}
			}
		},
    {
      "is_pinned": false,
      "is_approved": true,
      "service_ids": [
        61
      ],
      "author": {
        "avatar_url": null,
        "id": "designclever"
      },
      "thread_updated_at": "2015-05-31T02:32:24.000Z",
      "thread_updated_ts": 1433039544,
      "updated_at": "2015-06-01T16:43:47.028Z",
      "created_at": "2015-06-01T16:43:47.028Z",
      "images": [
        {
          "url": "https:\/\/40.media.tumblr.com\/02f509ae0c8ae35e326b27e2de65e6aa\/tumblr_np3fr8D7vg1qkxrtro1_1280.png",
          "caption": ""
        },
        {
          "url": "https:\/\/41.media.tumblr.com\/be2e05d0c23b95758b9f7a3a14ab2c10\/tumblr_np3fr8D7vg1qkxrtro2_1280.png",
          "caption": ""
        },
        {
          "url": "https:\/\/36.media.tumblr.com\/cb6a8e1ffaecbc086c0f93e9b456f5b1\/tumblr_np3fr8D7vg1qkxrtro3_1280.png",
          "caption": ""
        },
        {
          "url": "https:\/\/41.media.tumblr.com\/4ae18501c1d5835482024285ab8d64ad\/tumblr_np3fr8D7vg1qkxrtro4_1280.png",
          "caption": ""
        }
      ],
      "url": "http:\/\/designclever.tumblr.com\/post\/120315998180\/betype-36-days-36-type-designs-plus-1",
      "type_name": "photo",
      "feed_name": "tumblr",
      "body": null,
      "title": "<p><a href=\"http:\/\/betype.tumblr.com\/post\/120315679490\/36-days-36-type-designs-plus-1-by-alexander\" class=\"tumblr_blog\">betype<\/a>:<\/p>\n\n<blockquote><p><a href=\"https:\/\/www.behance.net\/gallery\/26221877\/36-Days-36-Type-Designs-(Plus-1)\">\n\n36 Days, 36 Type Designs (Plus 1) by\n\nAlexander Wright<\/a><br\/><\/p><\/blockquote>",
      "id": 3606
    },
    {
      "is_pinned": false,
      "is_approved": true,
      "service_ids": [
        61
      ],
      "author": {
        "avatar_url": null,
        "id": "designclever"
      },
      "thread_updated_at": "2015-05-31T02:02:48.000Z",
      "thread_updated_ts": 1433037768,
      "updated_at": "2015-06-01T16:43:47.146Z",
      "created_at": "2015-06-01T16:43:47.146Z",
      "images": [
        {
          "url": "https:\/\/40.media.tumblr.com\/a5678aec7ea356b77f38e10ae740f6f9\/tumblr_np6xoi8r7l1qa41hgo4_1280.jpg",
          "caption": ""
        },
        {
          "url": "https:\/\/41.media.tumblr.com\/cc35dae6f5e03ae3c7628d0a0a9dc996\/tumblr_np6xoi8r7l1qa41hgo1_1280.jpg",
          "caption": ""
        },
        {
          "url": "https:\/\/41.media.tumblr.com\/d20fdeb3a605fe9e7efe74e575b26177\/tumblr_np6xoi8r7l1qa41hgo2_1280.jpg",
          "caption": ""
        },
        {
          "url": "https:\/\/40.media.tumblr.com\/113bfccb59a5e25c305a9f883b550a6a\/tumblr_np6xoi8r7l1qa41hgo3_1280.jpg",
          "caption": ""
        }
      ],
      "url": "http:\/\/designclever.tumblr.com\/post\/120314023875\/buds-of-brooklyn-is-flower-company-based-in",
      "type_name": "photo",
      "feed_name": "tumblr",
      "body": null,
      "title": "<blockquote><p><small><i>Buds of Brooklyn is flower company based in Brooklyn, New York. I was lucky enough to have complete freedom in the direction of the branding. Flower photographs by Hannah Miles.<\/i><\/small><\/p><\/blockquote>",
      "id": 3607
    },
    {
      "is_pinned": false,
      "is_approved": true,
      "service_ids": [
        61
      ],
      "author": {
        "avatar_url": null,
        "id": "designclever"
      },
      "thread_updated_at": "2015-05-31T00:38:47.000Z",
      "thread_updated_ts": 1433032727,
      "updated_at": "2015-06-01T16:43:47.260Z",
      "created_at": "2015-06-01T16:43:47.260Z",
      "images": [
        {
          "url": "https:\/\/40.media.tumblr.com\/25f052668895cd0669173aace969c015\/tumblr_np3e3hiaGO1qkxrtro3_1280.jpg",
          "caption": ""
        },
        {
          "url": "https:\/\/40.media.tumblr.com\/9e5bdfaa37ddecba79244ba5baecaecf\/tumblr_np3e3hiaGO1qkxrtro1_1280.png",
          "caption": ""
        },
        {
          "url": "https:\/\/40.media.tumblr.com\/69e6ad7a990d971f3bcfe79385a80409\/tumblr_np3e3hiaGO1qkxrtro2_1280.jpg",
          "caption": ""
        }
      ],
      "url": "http:\/\/designclever.tumblr.com\/post\/120308751460\/betype-percusion-en-la-jungla-poster",
      "type_name": "photo",
      "feed_name": "tumblr",
      "body": null,
      "title": "<p><a href=\"http:\/\/betype.tumblr.com\/post\/120303987317\/percusion-en-la-jungla-poster-sinfonica\" class=\"tumblr_blog\">betype<\/a>:<\/p>\n\n<blockquote><p><a href=\"https:\/\/www.behance.net\/gallery\/26532947\/Percusion-en-la-jungla-Poster-Sinfonica\">\n\nPercusi\u00f3n en la jungla - Poster Sinf\u00f3nica by\n\nSantiago Villa Cardo\u00a0\/\n\nJuli\u00e1n Ram\u00edrez\u00a0\/\n\nDaniel Cuervo\u00a0\/\n\nJose Ladino<\/a><br\/><\/p><\/blockquote>",
      "id": 3608
    },
    {
      "is_pinned": false,
      "is_approved": true,
      "service_ids": [
        61
      ],
      "author": {
        "avatar_url": null,
        "id": "designclever"
      },
      "thread_updated_at": "2015-05-29T20:08:55.000Z",
      "thread_updated_ts": 1432930135,
      "updated_at": "2015-06-01T16:43:47.396Z",
      "created_at": "2015-06-01T16:43:47.396Z",
      "images": [
        {
          "url": "https:\/\/41.media.tumblr.com\/818c80a6363f4abcb4c02d51e7717369\/tumblr_np2vb4EYcR1r99d4ro1_1280.jpg",
          "caption": ""
        },
        {
          "url": "https:\/\/36.media.tumblr.com\/04cd89be954a6036624657ee92a19d68\/tumblr_np2vb4EYcR1r99d4ro2_1280.jpg",
          "caption": ""
        },
        {
          "url": "https:\/\/40.media.tumblr.com\/3653c4d268a86fd8c38a21287a2e0c46\/tumblr_np2vb4EYcR1r99d4ro3_1280.jpg",
          "caption": ""
        },
        {
          "url": "https:\/\/36.media.tumblr.com\/cd961780be61810f35dc408267019896\/tumblr_np2vb4EYcR1r99d4ro4_1280.jpg",
          "caption": ""
        },
        {
          "url": "https:\/\/40.media.tumblr.com\/f61c984c2e5b35824bb1035f1efc55ea\/tumblr_np2vb4EYcR1r99d4ro5_1280.jpg",
          "caption": ""
        },
        {
          "url": "https:\/\/41.media.tumblr.com\/11230999c49f48c9e7c4d327830cd90b\/tumblr_np2vb4EYcR1r99d4ro6_1280.jpg",
          "caption": ""
        },
        {
          "url": "https:\/\/41.media.tumblr.com\/d40665c156e75cfe539736b59ca522ff\/tumblr_np2vb4EYcR1r99d4ro7_1280.jpg",
          "caption": ""
        },
        {
          "url": "https:\/\/40.media.tumblr.com\/141798e803cba9e9feca3ca49580eb7d\/tumblr_np2vb4EYcR1r99d4ro8_1280.jpg",
          "caption": ""
        },
        {
          "url": "https:\/\/40.media.tumblr.com\/49d6bbdabf44164bcd1ca2bc94607fde\/tumblr_np2vb4EYcR1r99d4ro9_1280.jpg",
          "caption": ""
        }
      ],
      "url": "http:\/\/designclever.tumblr.com\/post\/120208645825\/arrangealign-design-by-futura-lovely-i",
      "type_name": "photo",
      "feed_name": "tumblr",
      "body": null,
      "title": "<p><a href=\"http:\/\/arrangealign.tumblr.com\/post\/120208111993\/design-by-futura-lovely-i-really-enjoy-this\" class=\"tumblr_blog\">arrangealign<\/a>:<\/p>\n\n<blockquote><p>Design by\u00a0<a href=\"https:\/\/www.behance.net\/MFutura\">Futura \u2014<\/a><\/p><p>Lovely! I really enjoy this project :)<\/p><\/blockquote>",
      "id": 3609
    },
    {
      "is_pinned": false,
      "is_approved": true,
      "service_ids": [
        61
      ],
      "author": {
        "avatar_url": null,
        "id": "designclever"
      },
      "thread_updated_at": "2015-05-29T14:49:46.000Z",
      "thread_updated_ts": 1432910986,
      "updated_at": "2015-06-01T16:43:47.535Z",
      "created_at": "2015-06-01T16:43:47.535Z",
      "images": [
        {
          "url": "https:\/\/41.media.tumblr.com\/73d38d728059d1664a6157cfe7edb098\/tumblr_np44qxgPFW1qd8wspo1_1280.jpg",
          "caption": ""
        }
      ],
      "url": "http:\/\/designclever.tumblr.com\/post\/120189129025\/thisiscatalogue-books-and-zines-we-published",
      "type_name": "photo",
      "feed_name": "tumblr",
      "body": null,
      "title": "<p><a href=\"http:\/\/blog.thisiscatalogue.co.uk\/post\/120184042956\/books-and-zines-we-published-for-offprint-london\" class=\"tumblr_blog\">thisiscatalogue<\/a>:<\/p>\n\n<blockquote><p>Books and zines we published for Offprint London last weekend are now all available to purchase via the <a href=\"http:\/\/www.cataloguelibrary.co.uk\">Catalogue Library<\/a> website.<br\/><\/p><\/blockquote>",
      "id": 3610
    },
    {
      "is_pinned": false,
      "is_approved": true,
      "service_ids": [
        61
      ],
      "author": {
        "avatar_url": null,
        "id": "designclever"
      },
      "thread_updated_at": "2015-05-29T14:49:33.000Z",
      "thread_updated_ts": 1432910973,
      "updated_at": "2015-06-01T16:43:47.652Z",
      "created_at": "2015-06-01T16:43:47.652Z",
      "images": [
        {
          "url": "https:\/\/41.media.tumblr.com\/866b169eef40db5d8d015d040deb1bed\/tumblr_np44aaDubU1r5tg6do1_1280.jpg",
          "caption": ""
        }
      ],
      "url": "http:\/\/designclever.tumblr.com\/post\/120189117175\/inspirimgrafik",
      "type_name": "photo",
      "feed_name": "tumblr",
      "body": null,
      "title": "<p><a href=\"http:\/\/inspirimgrafik.tumblr.com\/post\/120183562230\/http-www-cataloguelibrary-co-uk-city-so-nice-they\" class=\"tumblr_blog\">inspirimgrafik<\/a>:<\/p>\n\n<blockquote><p><a href=\"http:\/\/www.cataloguelibrary.co.uk\/city-so-nice-they-named-it-twice\/\">http:\/\/www.cataloguelibrary.co.uk\/city-so-nice-they-named-it-twice\/<\/a><br\/><\/p><\/blockquote>",
      "id": 3611
    },
    {
      "is_pinned": false,
      "is_approved": true,
      "service_ids": [
        61
      ],
      "author": {
        "avatar_url": null,
        "id": "designclever"
      },
      "thread_updated_at": "2015-05-29T14:23:19.000Z",
      "thread_updated_ts": 1432909399,
      "updated_at": "2015-06-01T16:43:47.779Z",
      "created_at": "2015-06-01T16:43:47.779Z",
      "images": [
        {
          "url": "https:\/\/41.media.tumblr.com\/64fb63f3b86d684642a50e2c0f7384bf\/tumblr_np47yvb1991spaqqfo3_1280.png",
          "caption": ""
        },
        {
          "url": "https:\/\/40.media.tumblr.com\/61856575f97df72b3f27db70deaa723e\/tumblr_np47yvb1991spaqqfo1_1280.png",
          "caption": ""
        },
        {
          "url": "https:\/\/40.media.tumblr.com\/bc6ccf609bb61b30e37f5bdc4223918c\/tumblr_np47yvb1991spaqqfo2_1280.png",
          "caption": ""
        }
      ],
      "url": "http:\/\/designclever.tumblr.com\/post\/120187671305\/cercle-is-a-typeface-extrapolated-from-the",
      "type_name": "photo",
      "feed_name": "tumblr",
      "body": null,
      "title": "<p>\u201cCercle is a typeface extrapolated from the heading of a 1914 (-1918) war magazine originated in France. The name behind &lsquo;Cercle&rsquo; is inspired by the circular grid used to create this unique and quirky typeface.<br\/><br\/>Wes Anderson&rsquo;s The Grand Budapest Hotel(2014 film) was used as a reference due to similarities in geometry, symmetry and quirky personality.\u201d<br\/><\/p><p><a href=\"http:\/\/www.seoyounglee.com\/\">SEO YOUNG LEE Studio<br\/> \u00a0 \u00a0 \u00a0 \u00a0\u2014Web, Graphic design<br\/>and Art Direction based<br\/>in Auckland, New Zealand.<\/a><br\/><\/p>",
      "id": 3612
    },
    {
      "is_pinned": false,
      "is_approved": true,
      "service_ids": [
        61
      ],
      "author": {
        "avatar_url": null,
        "id": "designclever"
      },
      "thread_updated_at": "2015-05-29T14:21:38.000Z",
      "thread_updated_ts": 1432909298,
      "updated_at": "2015-06-01T16:43:47.904Z",
      "created_at": "2015-06-01T16:43:47.904Z",
      "images": [
        {
          "url": "https:\/\/41.media.tumblr.com\/f3f312d407d1604875cd8de9b22e2770\/tumblr_np47w2WSuw1spaqqfo5_1280.jpg",
          "caption": ""
        },
        {
          "url": "https:\/\/40.media.tumblr.com\/1e61b84f61980ad16bb2546330a01ef6\/tumblr_np47w2WSuw1spaqqfo1_1280.jpg",
          "caption": ""
        },
        {
          "url": "https:\/\/41.media.tumblr.com\/0518ad5a1974c8af2a4c6c623e9ac3ff\/tumblr_np47w2WSuw1spaqqfo2_1280.jpg",
          "caption": ""
        },
        {
          "url": "https:\/\/40.media.tumblr.com\/aa6a751225410314b0f583872595bd47\/tumblr_np47w2WSuw1spaqqfo3_1280.jpg",
          "caption": ""
        },
        {
          "url": "https:\/\/40.media.tumblr.com\/1fe3bf72cd6115c65c1b39c92cb8ef9d\/tumblr_np47w2WSuw1spaqqfo4_1280.jpg",
          "caption": ""
        }
      ],
      "url": "http:\/\/designclever.tumblr.com\/post\/120187577155\/seo-young-lee-studio-web-graphic-design",
      "type_name": "photo",
      "feed_name": "tumblr",
      "body": null,
      "title": "<p><a href=\"http:\/\/www.seoyounglee.com\/\">SEO YOUNG LEE Studio<br\/> \u00a0 \u00a0 \u00a0 \u00a0\u2014Web, Graphic design<br\/>and Art Direction based<br\/>in Auckland, New Zealand.<\/a><br\/><\/p>",
      "id": 3613
    },
    {
      "is_pinned": false,
      "is_approved": true,
      "service_ids": [
        61
      ],
      "author": {
        "avatar_url": null,
        "id": "designclever"
      },
      "thread_updated_at": "2015-05-29T14:14:13.000Z",
      "thread_updated_ts": 1432908853,
      "updated_at": "2015-06-01T16:43:48.009Z",
      "created_at": "2015-06-01T16:43:48.009Z",
      "images": [
        {
          "url": "https:\/\/40.media.tumblr.com\/7fc3ad0452ce3cae2e81110afc84a999\/tumblr_np3tihz4UE1qzqavpo1_1280.jpg",
          "caption": ""
        }
      ],
      "url": "http:\/\/designclever.tumblr.com\/post\/120187170190\/andren-via-groszcolab-dtd-lp2-03-jpg",
      "type_name": "photo",
      "feed_name": "tumblr",
      "body": null,
      "title": "<p><a href=\"http:\/\/andren.tumblr.com\/post\/120174888382\/via-groszcolab-dtd-lp2-03-jpg-1200x800\" class=\"tumblr_blog\">andren<\/a>:<\/p>\n\n<blockquote><p>(via <a href=\"http:\/\/www.groszcolab.com.au\/content\/images\/homepage\/GROSZCOLAB_DTD_LP2_03.jpg\">GROSZCOLAB_DTD_LP2_03.jpg (1200\u00d7800)<\/a>) <\/p><\/blockquote>",
      "id": 3614
    },
    {
      "is_pinned": false,
      "is_approved": true,
      "service_ids": [
        61
      ],
      "author": {
        "avatar_url": null,
        "id": "designclever"
      },
      "thread_updated_at": "2015-05-29T14:09:47.000Z",
      "thread_updated_ts": 1432908587,
      "updated_at": "2015-06-01T16:43:48.134Z",
      "created_at": "2015-06-01T16:43:48.134Z",
      "images": [
        {
          "url": "https:\/\/41.media.tumblr.com\/441645cecdc4b3bb18363a8959a0198e\/tumblr_np47cbvpEZ1spaqqfo1_1280.jpg",
          "caption": ""
        }
      ],
      "url": "http:\/\/designclever.tumblr.com\/post\/120186937020\/bushwick-icons-by-marianna-fierro",
      "type_name": "photo",
      "feed_name": "tumblr",
      "body": null,
      "title": "<p>Bushwick Icons By <a href=\"https:\/\/dribbble.com\/mariannafierro\">Marianna Fierro<\/a><br\/><\/p>",
      "id": 3615
    },
    {
      "is_pinned": false,
      "is_approved": true,
      "service_ids": [
        61
      ],
      "author": {
        "avatar_url": null,
        "id": "designclever"
      },
      "thread_updated_at": "2015-05-29T14:05:02.000Z",
      "thread_updated_ts": 1432908302,
      "updated_at": "2015-06-01T16:43:48.278Z",
      "created_at": "2015-06-01T16:43:48.278Z",
      "images": [
        {
          "url": "https:\/\/36.media.tumblr.com\/5eb68e58b7a66ac41468fa2e1f376439\/tumblr_np474eKKNT1spaqqfo1_1280.jpg",
          "caption": ""
        }
      ],
      "url": "http:\/\/designclever.tumblr.com\/post\/120186685770\/this-branding-project-includes-a-new-logo-and",
      "type_name": "photo",
      "feed_name": "tumblr",
      "body": null,
      "title": "<p>This branding project includes a new logo and identity for a bubble tea cafe located in New Paltz, NY named Quick Sip. The price range for the bubble tea is between $3-4, and the targeted audience is adults and children looking for a small snack in between meals or a treat after dinner. Quick Sip wants to express a friendly, cute, comfortable, whimsical, light, soft, and inviting brand.<br\/><\/p><p>By <a href=\"http:\/\/mackenziepalma.com\/work\/quicksip.php\">Mackenzie Palma<\/a><\/p>",
      "id": 3616
    },
    {
      "is_pinned": false,
      "is_approved": true,
      "service_ids": [
        61
      ],
      "author": {
        "avatar_url": null,
        "id": "designclever"
      },
      "thread_updated_at": "2015-05-29T14:03:06.000Z",
      "thread_updated_ts": 1432908186,
      "updated_at": "2015-06-01T16:43:48.422Z",
      "created_at": "2015-06-01T16:43:48.422Z",
      "images": [
        {
          "url": "https:\/\/41.media.tumblr.com\/e29c9f7195ace52facc149d092b01ff1\/tumblr_np4716OMNy1spaqqfo1_1280.jpg",
          "caption": ""
        }
      ],
      "url": "http:\/\/designclever.tumblr.com\/post\/120186585745\/r-cubed-by-dimitris-florakis",
      "type_name": "photo",
      "feed_name": "tumblr",
      "body": null,
      "title": "<p>R-CUBED by\u00a0<a href=\"https:\/\/www.behance.net\/roiber\">Dimitris Florakis<\/a><\/p>",
      "id": 3617
    },
    {
      "is_pinned": false,
      "is_approved": true,
      "service_ids": [
        61
      ],
      "author": {
        "avatar_url": null,
        "id": "designclever"
      },
      "thread_updated_at": "2015-05-29T13:58:26.000Z",
      "thread_updated_ts": 1432907906,
      "updated_at": "2015-06-01T16:43:48.559Z",
      "created_at": "2015-06-01T16:43:48.559Z",
      "images": [
        {
          "url": "https:\/\/41.media.tumblr.com\/e98cdd20675e54a0834ce3295f1eee1f\/tumblr_nomogwKEYp1spaqqfo1_540.jpg",
          "caption": ""
        }
      ],
      "url": "http:\/\/designclever.tumblr.com\/post\/120186329495\/classic-monsters-by-el-inmigrante-facebook",
      "type_name": "photo",
      "feed_name": "tumblr",
      "body": null,
      "title": "<p>Classic Monsters by\u00a0<a href=\"http:\/\/elinmigrantedesign.tumblr.com\/\">El Inmigrante<\/a>.<\/p>\n<p><a href=\"https:\/\/www.facebook.com\/elinmigrantedesign\">Facebook<\/a><\/p>",
      "id": 3618
    },
    {
      "is_pinned": false,
      "is_approved": true,
      "service_ids": [
        61
      ],
      "author": {
        "avatar_url": null,
        "id": "designclever"
      },
      "thread_updated_at": "2015-05-29T13:58:21.000Z",
      "thread_updated_ts": 1432907901,
      "updated_at": "2015-06-01T16:43:48.682Z",
      "created_at": "2015-06-01T16:43:48.682Z",
      "images": [
        {
          "url": "https:\/\/36.media.tumblr.com\/817c2ccbd657c5e6b821642258c538ff\/tumblr_nomwnlZFHA1spaqqfo1_1280.jpg",
          "caption": ""
        }
      ],
      "url": "http:\/\/designclever.tumblr.com\/post\/120186325575\/the-round-square-teaware-meeting-the-basic",
      "type_name": "photo",
      "feed_name": "tumblr",
      "body": null,
      "title": "<p><b>The Round Square Teaware<\/b><\/p>\n<p>Meeting the basic functionality requirement aside, how do we add something decorative which is both tangible yet simple and able to form an emotional feeling to an object?<\/p>\n<p>Neither round, nor square. It is round, and also square.<\/p>\n<p>Square and round are both elemental forms of nature, orbital track of motion, or structural element of a form. Oriental people study the law of the universe and emulate nature, and from that they create objects. On a spiritual level, they also assimilate them into way of life.<\/p>\n<p>Holding water is a logical &amp; natural manifestation of the round mug. Adding a cube on its surface, IS a human expression, an act that ingeniously directs one\u2019s visual orientation, and confer an expression upon the mug.<\/p>\n<p><b>Project title:<\/b> The Round Square Teaware<br\/><b>Brand:<\/b> KOAN+<br\/><b>Designer:<\/b> Chuntso Liu<br\/><b>Location:<\/b>\u00a0Taiwan<br\/><b>Year:<\/b> 2015<\/p>",
      "id": 3619
    },
    {
      "is_pinned": false,
      "is_approved": true,
      "service_ids": [
        61
      ],
      "author": {
        "avatar_url": null,
        "id": "designclever"
      },
      "thread_updated_at": "2015-05-29T13:57:38.000Z",
      "thread_updated_ts": 1432907858,
      "updated_at": "2015-06-01T16:43:48.801Z",
      "created_at": "2015-06-01T16:43:48.801Z",
      "images": [
        {
          "url": "https:\/\/40.media.tumblr.com\/77e764bba7b9353eb0b5f19f19fbf2ae\/tumblr_np46s2BIHs1spaqqfo1_1280.png",
          "caption": ""
        }
      ],
      "url": "http:\/\/designclever.tumblr.com\/post\/120186289270\/get-up-and-ride-illustrations-by-marianna-fierro",
      "type_name": "photo",
      "feed_name": "tumblr",
      "body": null,
      "title": "<p>Get Up and Ride Illustrations By <a href=\"https:\/\/dribbble.com\/mariannafierro\">Marianna Fierro<\/a><br\/><\/p>",
      "id": 3620
    },
    {
      "is_pinned": false,
      "is_approved": true,
      "service_ids": [
        61
      ],
      "author": {
        "avatar_url": null,
        "id": "designclever"
      },
      "thread_updated_at": "2015-05-29T13:49:10.000Z",
      "thread_updated_ts": 1432907350,
      "updated_at": "2015-06-01T16:43:48.909Z",
      "created_at": "2015-06-01T16:43:48.909Z",
      "images": [
        {
          "url": "https:\/\/40.media.tumblr.com\/726fcb47a4d96a23b6ce6efe282339fb\/tumblr_np2261uzYQ1spaqqfo1_1280.jpg",
          "caption": ""
        }
      ],
      "url": "http:\/\/designclever.tumblr.com\/post\/120185841410\/gekox-apparel-for-more-hit-the-link-bellow",
      "type_name": "photo",
      "feed_name": "tumblr",
      "body": null,
      "title": "<p>Gekox \u229f apparel<br\/>-<br\/>For more, hit the link bellow:<br\/><a href=\"https:\/\/www.behance.net\/gallery\/26443391\/Gekox-collection\">https:\/\/www.behance.net\/gallery\/26443391\/Gekox-collection<\/a><\/p>",
      "id": 3621
    },
    {
      "is_pinned": false,
      "is_approved": true,
      "service_ids": [
        61
      ],
      "author": {
        "avatar_url": null,
        "id": "designclever"
      },
      "thread_updated_at": "2015-05-29T13:49:05.000Z",
      "thread_updated_ts": 1432907345,
      "updated_at": "2015-06-01T16:43:49.035Z",
      "created_at": "2015-06-01T16:43:49.035Z",
      "images": [
        {
          "url": "https:\/\/36.media.tumblr.com\/da7397b188b504559a76477ad438571c\/tumblr_np227edrvE1spaqqfo1_1280.jpg",
          "caption": ""
        }
      ],
      "url": "http:\/\/designclever.tumblr.com\/post\/120185837885\/gekox-apparel-for-more-hit-the-link-bellow",
      "type_name": "photo",
      "feed_name": "tumblr",
      "body": null,
      "title": "<p>Gekox \u229f apparel<br\/>-<br\/>For more, hit the link bellow:<br\/><a href=\"https:\/\/www.behance.net\/gallery\/26443391\/Gekox-collection\">https:\/\/www.behance.net\/gallery\/26443391\/Gekox-collection<\/a><\/p>",
      "id": 3622
    },
    {
      "is_pinned": false,
      "is_approved": true,
      "service_ids": [
        61
      ],
      "author": {
        "avatar_url": null,
        "id": "designclever"
      },
      "thread_updated_at": "2015-05-29T13:49:01.000Z",
      "thread_updated_ts": 1432907341,
      "updated_at": "2015-06-01T16:43:49.143Z",
      "created_at": "2015-06-01T16:43:49.143Z",
      "images": [
        {
          "url": "https:\/\/41.media.tumblr.com\/69291860b138d476a1908aa877693bff\/tumblr_np228biGz91spaqqfo1_1280.jpg",
          "caption": ""
        }
      ],
      "url": "http:\/\/designclever.tumblr.com\/post\/120185834180\/gekox-apparel-for-more-hit-the-link-bellow",
      "type_name": "photo",
      "feed_name": "tumblr",
      "body": null,
      "title": "<p>Gekox \u229f apparel<br\/>-<br\/>For more, hit the link bellow:<br\/><a href=\"https:\/\/www.behance.net\/gallery\/26443391\/Gekox-collection\">https:\/\/www.behance.net\/gallery\/26443391\/Gekox-collection<\/a><\/p>",
      "id": 3623
    },
    {
      "is_pinned": false,
      "is_approved": true,
      "service_ids": [
        61
      ],
      "author": {
        "avatar_url": null,
        "id": "designclever"
      },
      "thread_updated_at": "2015-05-29T13:48:56.000Z",
      "thread_updated_ts": 1432907336,
      "updated_at": "2015-06-01T16:43:49.271Z",
      "created_at": "2015-06-01T16:43:49.271Z",
      "images": [
        {
          "url": "https:\/\/40.media.tumblr.com\/a2bb8a670320798c9b216d068619e30f\/tumblr_np229jcox21spaqqfo1_1280.jpg",
          "caption": ""
        }
      ],
      "url": "http:\/\/designclever.tumblr.com\/post\/120185830190\/gekox-apparel-for-more-hit-the-link-bellow",
      "type_name": "photo",
      "feed_name": "tumblr",
      "body": null,
      "title": "<p>Gekox \u229f apparel<br\/>-<br\/>For more, hit the link bellow:<br\/><a href=\"https:\/\/www.behance.net\/gallery\/26443391\/Gekox-collection\">https:\/\/www.behance.net\/gallery\/26443391\/Gekox-collection<\/a><\/p>",
      "id": 3624
    },
    {
      "is_pinned": false,
      "is_approved": true,
      "service_ids": [
        61
      ],
      "author": {
        "avatar_url": null,
        "id": "designclever"
      },
      "thread_updated_at": "2015-05-29T13:48:50.000Z",
      "thread_updated_ts": 1432907330,
      "updated_at": "2015-06-01T16:43:49.392Z",
      "created_at": "2015-06-01T16:43:49.392Z",
      "images": [
        {
          "url": "https:\/\/41.media.tumblr.com\/7563bea5bda4871fe50e666853c43371\/tumblr_np22b0x60D1spaqqfo1_1280.jpg",
          "caption": ""
        }
      ],
      "url": "http:\/\/designclever.tumblr.com\/post\/120185825425\/gekox-apparel-for-more-hit-the-link-bellow",
      "type_name": "photo",
      "feed_name": "tumblr",
      "body": null,
      "title": "<p>Gekox \u229f apparel<br\/>-<br\/>For more, hit the link bellow:<br\/><a href=\"https:\/\/www.behance.net\/gallery\/26443391\/Gekox-collection\">https:\/\/www.behance.net\/gallery\/26443391\/Gekox-collection<\/a><\/p>",
      "id": 3625
    },
    {
      "is_pinned": false,
      "is_approved": true,
      "service_ids": [
        57
      ],
      "author": {
        "avatar_url": "http:\/\/pbs.twimg.com\/profile_images\/445588675754090498\/nsGAtnRi_normal.png",
        "id": "bitovi"
      },
      "thread_updated_at": "2015-05-28T15:59:55.000Z",
      "thread_updated_ts": 1432828795,
      "updated_at": "2015-06-01T16:39:56.677Z",
      "created_at": "2015-06-01T16:39:56.677Z",
      "images": [],
      "url": "https:\/\/twitter.com\/bitovi\/status\/603953858910425089",
      "type_name": "tweet",
      "feed_name": "twitter",
      "body": null,
      "title": "Training Series \u2013 Closures <a href=\"http:\/\/t.co\/G4HvHUKbrK\" rel=\"nofollow\">http:\/\/t.co\/G4HvHUKbrK<\/a> via @<a class=\"tweet-url username\" href=\"https:\/\/twitter.com\/bitovi\" rel=\"nofollow\">bitovi<\/a>",
      "id": 3390
    },
    {
      "is_pinned": false,
      "is_approved": true,
      "service_ids": [
        57
      ],
      "author": {
        "avatar_url": "http:\/\/pbs.twimg.com\/profile_images\/445588675754090498\/nsGAtnRi_normal.png",
        "id": "bitovi"
      },
      "thread_updated_at": "2015-05-28T03:41:54.000Z",
      "thread_updated_ts": 1432784514,
      "updated_at": "2015-06-01T16:39:56.868Z",
      "created_at": "2015-06-01T16:39:56.868Z",
      "images": [],
      "url": "https:\/\/twitter.com\/bitovi\/status\/603768130142400512",
      "type_name": "tweet",
      "feed_name": "twitter",
      "body": null,
      "title": "RT @<a class=\"tweet-url username\" href=\"https:\/\/twitter.com\/daniel_franz\" rel=\"nofollow\">daniel_franz<\/a>: Great stuff, just watched that episode on YouTube <a href=\"https:\/\/t.co\/AlJti6BKJC\" rel=\"nofollow\">https:\/\/t.co\/AlJti6BKJC<\/a> <a href=\"https:\/\/t.co\/2jsDNh91gC\" rel=\"nofollow\">https:\/\/t.co\/2jsDNh91gC<\/a>",
      "id": 3391
    },
    {
      "is_pinned": false,
      "is_approved": true,
      "service_ids": [
        57
      ],
      "author": {
        "avatar_url": "http:\/\/pbs.twimg.com\/profile_images\/445588675754090498\/nsGAtnRi_normal.png",
        "id": "bitovi"
      },
      "thread_updated_at": "2015-05-27T17:05:31.000Z",
      "thread_updated_ts": 1432746331,
      "updated_at": "2015-06-01T16:39:56.980Z",
      "created_at": "2015-06-01T16:39:56.980Z",
      "images": [],
      "url": "https:\/\/twitter.com\/bitovi\/status\/603607981020684288",
      "type_name": "tweet",
      "feed_name": "twitter",
      "body": null,
      "title": "And we're live! Closures de-mystified: <a href=\"https:\/\/t.co\/XKVk0QC5LU\" rel=\"nofollow\">https:\/\/t.co\/XKVk0QC5LU<\/a> <a class=\"tweet-url hashtag\" href=\"https:\/\/twitter.com\/#!\/search?q=%23JavaScript\" rel=\"nofollow\" title=\"#JavaScript\">#JavaScript<\/a>",
      "id": 3392
    },
    {
      "is_pinned": false,
      "is_approved": true,
      "service_ids": [
        57
      ],
      "author": {
        "avatar_url": "http:\/\/pbs.twimg.com\/profile_images\/445588675754090498\/nsGAtnRi_normal.png",
        "id": "bitovi"
      },
      "thread_updated_at": "2015-05-27T16:20:58.000Z",
      "thread_updated_ts": 1432743658,
      "updated_at": "2015-06-01T16:39:57.106Z",
      "created_at": "2015-06-01T16:39:57.106Z",
      "images": [],
      "url": "https:\/\/twitter.com\/bitovi\/status\/603596768442327041",
      "type_name": "tweet",
      "feed_name": "twitter",
      "body": null,
      "title": "Join us in ~40 min we discuss closure scope in JS as we continue our training series! <a href=\"https:\/\/t.co\/XKVk0QC5LU\" rel=\"nofollow\">https:\/\/t.co\/XKVk0QC5LU<\/a> <a class=\"tweet-url hashtag\" href=\"https:\/\/twitter.com\/#!\/search?q=%23JavaScript\" rel=\"nofollow\" title=\"#JavaScript\">#JavaScript<\/a> <a class=\"tweet-url hashtag\" href=\"https:\/\/twitter.com\/#!\/search?q=%23training\" rel=\"nofollow\" title=\"#training\">#training<\/a>",
      "id": 3393
    },
    {
      "is_pinned": false,
      "is_approved": true,
      "service_ids": [
        57
      ],
      "author": {
        "avatar_url": "http:\/\/pbs.twimg.com\/profile_images\/445588675754090498\/nsGAtnRi_normal.png",
        "id": "bitovi"
      },
      "thread_updated_at": "2015-05-27T04:14:22.000Z",
      "thread_updated_ts": 1432700062,
      "updated_at": "2015-06-01T16:39:57.225Z",
      "created_at": "2015-06-01T16:39:57.225Z",
      "images": [
        {
          "url": "http:\/\/pbs.twimg.com\/media\/CF9r_7TUgAAr1hy.jpg"
        }
      ],
      "url": "https:\/\/twitter.com\/bitovi\/status\/603413914471297024",
      "type_name": "tweet",
      "feed_name": "twitter",
      "body": null,
      "title": "RT @<a class=\"tweet-url username\" href=\"https:\/\/twitter.com\/amyjollymore\" rel=\"nofollow\">amyjollymore<\/a>: Pro @<a class=\"tweet-url username\" href=\"https:\/\/twitter.com\/tomgreever\" rel=\"nofollow\">tomgreever<\/a> in studio today! Recording <a class=\"tweet-url hashtag\" href=\"https:\/\/twitter.com\/#!\/search?q=%23ArticulatingDesignDecisions\" rel=\"nofollow\" title=\"#ArticulatingDesignDecisions\">#ArticulatingDesignDecisions<\/a> What a natural. @<a class=\"tweet-url username\" href=\"https:\/\/twitter.com\/OReillyMedia\" rel=\"nofollow\">OReillyMedia<\/a> @<a class=\"tweet-url username\" href=\"https:\/\/twitter.com\/oreillydesign\" rel=\"nofollow\">oreillydesign<\/a> http\u2026",
      "id": 3394
    },
    {
      "is_pinned": false,
      "is_approved": true,
      "service_ids": [
        57
      ],
      "author": {
        "avatar_url": "http:\/\/pbs.twimg.com\/profile_images\/445588675754090498\/nsGAtnRi_normal.png",
        "id": "bitovi"
      },
      "thread_updated_at": "2015-05-27T02:20:21.000Z",
      "thread_updated_ts": 1432693221,
      "updated_at": "2015-06-01T16:39:57.351Z",
      "created_at": "2015-06-01T16:39:57.351Z",
      "images": [],
      "url": "https:\/\/twitter.com\/bitovi\/status\/603385219270475777",
      "type_name": "tweet",
      "feed_name": "twitter",
      "body": null,
      "title": "RT @<a class=\"tweet-url username\" href=\"https:\/\/twitter.com\/air_hadoken\" rel=\"nofollow\">air_hadoken<\/a>: Finally got around to watching this short vid about @<a class=\"tweet-url username\" href=\"https:\/\/twitter.com\/stealjs\" rel=\"nofollow\">stealjs<\/a> from March, wherein @<a class=\"tweet-url username\" href=\"https:\/\/twitter.com\/justinbmeyer\" rel=\"nofollow\">justinbmeyer<\/a> is blowing my mind:  https:\u2026",
      "id": 3395
    },
    {
      "is_pinned": false,
      "is_approved": true,
      "service_ids": [
        57
      ],
      "author": {
        "avatar_url": "http:\/\/pbs.twimg.com\/profile_images\/445588675754090498\/nsGAtnRi_normal.png",
        "id": "bitovi"
      },
      "thread_updated_at": "2015-05-26T23:59:04.000Z",
      "thread_updated_ts": 1432684744,
      "updated_at": "2015-06-01T16:39:57.462Z",
      "created_at": "2015-06-01T16:39:57.462Z",
      "images": [
        {
          "url": "http:\/\/pbs.twimg.com\/media\/CF8zip0UgAAy66u.jpg"
        }
      ],
      "url": "https:\/\/twitter.com\/bitovi\/status\/603349663631187968",
      "type_name": "tweet",
      "feed_name": "twitter",
      "body": null,
      "title": "RT @<a class=\"tweet-url username\" href=\"https:\/\/twitter.com\/tomgreever\" rel=\"nofollow\">tomgreever<\/a>: At @<a class=\"tweet-url username\" href=\"https:\/\/twitter.com\/OReillyMedia\" rel=\"nofollow\">OReillyMedia<\/a> studio in Sebastopol, CA shooting Articulating Design Decisions, THE MOVIE <a class=\"tweet-url hashtag\" href=\"https:\/\/twitter.com\/#!\/search?q=%23ux\" rel=\"nofollow\" title=\"#ux\">#ux<\/a> <a href=\"http:\/\/t.co\/oO8w2ODsAk\" rel=\"nofollow\">http:\/\/t.co\/oO8w2ODsAk<\/a>",
      "id": 3396
    },
    {
      "is_pinned": false,
      "is_approved": true,
      "service_ids": [
        57
      ],
      "author": {
        "avatar_url": "http:\/\/pbs.twimg.com\/profile_images\/445588675754090498\/nsGAtnRi_normal.png",
        "id": "bitovi"
      },
      "thread_updated_at": "2015-05-26T22:00:04.000Z",
      "thread_updated_ts": 1432677604,
      "updated_at": "2015-06-01T16:39:57.591Z",
      "created_at": "2015-06-01T16:39:57.591Z",
      "images": [],
      "url": "https:\/\/twitter.com\/bitovi\/status\/603319718544416768",
      "type_name": "tweet",
      "feed_name": "twitter",
      "body": null,
      "title": "Join us tomorrow for the next installment of our JS Training Series: Closures! <a href=\"http:\/\/t.co\/pcju8p1fLd\" rel=\"nofollow\">http:\/\/t.co\/pcju8p1fLd<\/a> <a class=\"tweet-url hashtag\" href=\"https:\/\/twitter.com\/#!\/search?q=%23JavaScript\" rel=\"nofollow\" title=\"#JavaScript\">#JavaScript<\/a>",
      "id": 3397
    },
    {
      "is_pinned": false,
      "is_approved": true,
      "service_ids": [
        57
      ],
      "author": {
        "avatar_url": "http:\/\/pbs.twimg.com\/profile_images\/445588675754090498\/nsGAtnRi_normal.png",
        "id": "bitovi"
      },
      "thread_updated_at": "2015-05-23T06:47:16.000Z",
      "thread_updated_ts": 1432363636,
      "updated_at": "2015-06-01T16:39:57.717Z",
      "created_at": "2015-06-01T16:39:57.717Z",
      "images": [],
      "url": "https:\/\/twitter.com\/bitovi\/status\/602002840303771648",
      "type_name": "tweet",
      "feed_name": "twitter",
      "body": null,
      "title": "RT @<a class=\"tweet-url username\" href=\"https:\/\/twitter.com\/justinbmeyer\" rel=\"nofollow\">justinbmeyer<\/a>: C3 custom elements for CanJS: <a href=\"http:\/\/t.co\/QBe1GP01uJ\" rel=\"nofollow\">http:\/\/t.co\/QBe1GP01uJ<\/a> by @<a class=\"tweet-url username\" href=\"https:\/\/twitter.com\/MrKyleGifford\" rel=\"nofollow\">MrKyleGifford<\/a> !",
      "id": 3398
    },
    {
      "is_pinned": false,
      "is_approved": true,
      "service_ids": [
        57
      ],
      "author": {
        "avatar_url": "http:\/\/pbs.twimg.com\/profile_images\/445588675754090498\/nsGAtnRi_normal.png",
        "id": "bitovi"
      },
      "thread_updated_at": "2015-05-23T06:47:13.000Z",
      "thread_updated_ts": 1432363633,
      "updated_at": "2015-06-01T16:39:57.838Z",
      "created_at": "2015-06-01T16:39:57.838Z",
      "images": [],
      "url": "https:\/\/twitter.com\/bitovi\/status\/602002828014452737",
      "type_name": "tweet",
      "feed_name": "twitter",
      "body": null,
      "title": "RT @<a class=\"tweet-url username\" href=\"https:\/\/twitter.com\/cklanac\" rel=\"nofollow\">cklanac<\/a>: Building Amazing Single Page Apps with CanJS and StealJS <a href=\"http:\/\/t.co\/GWVEBTwrJd\" rel=\"nofollow\">http:\/\/t.co\/GWVEBTwrJd<\/a>",
      "id": 3399
    },
    {
      "is_pinned": false,
      "is_approved": true,
      "service_ids": [
        57
      ],
      "author": {
        "avatar_url": "http:\/\/pbs.twimg.com\/profile_images\/445588675754090498\/nsGAtnRi_normal.png",
        "id": "bitovi"
      },
      "thread_updated_at": "2015-05-22T21:17:01.000Z",
      "thread_updated_ts": 1432329421,
      "updated_at": "2015-06-01T16:39:57.992Z",
      "created_at": "2015-06-01T16:39:57.992Z",
      "images": [],
      "url": "https:\/\/twitter.com\/bitovi\/status\/601859330367959040",
      "type_name": "tweet",
      "feed_name": "twitter",
      "body": null,
      "title": "RT @<a class=\"tweet-url username\" href=\"https:\/\/twitter.com\/The_Lela\" rel=\"nofollow\">The_Lela<\/a>: I can't share most of my @<a class=\"tweet-url username\" href=\"https:\/\/twitter.com\/bitovi\" rel=\"nofollow\">bitovi<\/a> work, but @<a class=\"tweet-url username\" href=\"https:\/\/twitter.com\/SamsClub\" rel=\"nofollow\">SamsClub<\/a> just went live with the Tire Finder I helped with <a href=\"http:\/\/t.co\/Ea40pgbNrn\" rel=\"nofollow\">http:\/\/t.co\/Ea40pgbNrn<\/a>",
      "id": 3400
    },
    {
      "is_pinned": false,
      "is_approved": true,
      "service_ids": [
        57
      ],
      "author": {
        "avatar_url": "http:\/\/pbs.twimg.com\/profile_images\/445588675754090498\/nsGAtnRi_normal.png",
        "id": "bitovi"
      },
      "thread_updated_at": "2015-05-22T21:16:58.000Z",
      "thread_updated_ts": 1432329418,
      "updated_at": "2015-06-01T16:39:58.143Z",
      "created_at": "2015-06-01T16:39:58.143Z",
      "images": [
        {
          "url": "http:\/\/pbs.twimg.com\/media\/CFo70WBW0AE_GnN.jpg"
        }
      ],
      "url": "https:\/\/twitter.com\/bitovi\/status\/601859318510710784",
      "type_name": "tweet",
      "feed_name": "twitter",
      "body": null,
      "title": "RT @<a class=\"tweet-url username\" href=\"https:\/\/twitter.com\/Alfredo_Delgado\" rel=\"nofollow\">Alfredo_Delgado<\/a>: This week, last year, flying into Chicago for my @<a class=\"tweet-url username\" href=\"https:\/\/twitter.com\/bitovi\" rel=\"nofollow\">bitovi<\/a> interview. <a href=\"http:\/\/t.co\/1Il8AzKSQU\" rel=\"nofollow\">http:\/\/t.co\/1Il8AzKSQU<\/a>",
      "id": 3401
    },
    {
      "is_pinned": false,
      "is_approved": true,
      "service_ids": [
        57
      ],
      "author": {
        "avatar_url": "http:\/\/pbs.twimg.com\/profile_images\/445588675754090498\/nsGAtnRi_normal.png",
        "id": "bitovi"
      },
      "thread_updated_at": "2015-05-21T22:14:05.000Z",
      "thread_updated_ts": 1432246445,
      "updated_at": "2015-06-01T16:39:58.315Z",
      "created_at": "2015-06-01T16:39:58.315Z",
      "images": [],
      "url": "https:\/\/twitter.com\/bitovi\/status\/601511304948494337",
      "type_name": "tweet",
      "feed_name": "twitter",
      "body": null,
      "title": "CanJS 2.2.6 released <a href=\"http:\/\/t.co\/lDfITIyJVC\" rel=\"nofollow\">http:\/\/t.co\/lDfITIyJVC<\/a> via @<a class=\"tweet-url username\" href=\"https:\/\/twitter.com\/bitovi\" rel=\"nofollow\">bitovi<\/a>",
      "id": 3402
    },
    {
      "is_pinned": false,
      "is_approved": true,
      "service_ids": [
        57
      ],
      "author": {
        "avatar_url": "http:\/\/pbs.twimg.com\/profile_images\/445588675754090498\/nsGAtnRi_normal.png",
        "id": "bitovi"
      },
      "thread_updated_at": "2015-05-21T03:01:59.000Z",
      "thread_updated_ts": 1432177319,
      "updated_at": "2015-06-01T16:39:58.446Z",
      "created_at": "2015-06-01T16:39:58.446Z",
      "images": [],
      "url": "https:\/\/twitter.com\/bitovi\/status\/601221370886934528",
      "type_name": "tweet",
      "feed_name": "twitter",
      "body": null,
      "title": "RT @<a class=\"tweet-url username\" href=\"https:\/\/twitter.com\/adrifolio\" rel=\"nofollow\">adrifolio<\/a>: @<a class=\"tweet-url username\" href=\"https:\/\/twitter.com\/m_mujica\" rel=\"nofollow\">m_mujica<\/a> @<a class=\"tweet-url username\" href=\"https:\/\/twitter.com\/bitovi\" rel=\"nofollow\">bitovi<\/a> It's the best! So happy to have you on board!",
      "id": 3403
    },
    {
      "is_pinned": false,
      "is_approved": true,
      "service_ids": [
        57
      ],
      "author": {
        "avatar_url": "http:\/\/pbs.twimg.com\/profile_images\/445588675754090498\/nsGAtnRi_normal.png",
        "id": "bitovi"
      },
      "thread_updated_at": "2015-05-20T21:10:19.000Z",
      "thread_updated_ts": 1432156219,
      "updated_at": "2015-06-01T16:39:58.569Z",
      "created_at": "2015-06-01T16:39:58.569Z",
      "images": [],
      "url": "https:\/\/twitter.com\/bitovi\/status\/601132868455124992",
      "type_name": "tweet",
      "feed_name": "twitter",
      "body": null,
      "title": "Some technology debates are like fixing a paint chip on the Titanic as it heads full speed towards an iceberg. Focus on what matters.",
      "id": 3404
    },
    {
      "is_pinned": false,
      "is_approved": true,
      "service_ids": [
        57
      ],
      "author": {
        "avatar_url": "http:\/\/pbs.twimg.com\/profile_images\/445588675754090498\/nsGAtnRi_normal.png",
        "id": "bitovi"
      },
      "thread_updated_at": "2015-05-20T21:02:56.000Z",
      "thread_updated_ts": 1432155776,
      "updated_at": "2015-06-01T16:39:58.692Z",
      "created_at": "2015-06-01T16:39:58.692Z",
      "images": [],
      "url": "https:\/\/twitter.com\/bitovi\/status\/601131013113151488",
      "type_name": "tweet",
      "feed_name": "twitter",
      "body": null,
      "title": "JavaScript Frameworks Don\u2019t Matter \u2013 The Real Reasons Why Projects Fail <a href=\"http:\/\/t.co\/R7AecLMhcJ\" rel=\"nofollow\">http:\/\/t.co\/R7AecLMhcJ<\/a> via @<a class=\"tweet-url username\" href=\"https:\/\/twitter.com\/bitovi\" rel=\"nofollow\">bitovi<\/a>",
      "id": 3405
    },
    {
      "is_pinned": false,
      "is_approved": true,
      "service_ids": [
        57
      ],
      "author": {
        "avatar_url": "http:\/\/pbs.twimg.com\/profile_images\/445588675754090498\/nsGAtnRi_normal.png",
        "id": "bitovi"
      },
      "thread_updated_at": "2015-05-20T17:50:43.000Z",
      "thread_updated_ts": 1432144243,
      "updated_at": "2015-06-01T16:39:58.812Z",
      "created_at": "2015-06-01T16:39:58.812Z",
      "images": [],
      "url": "https:\/\/twitter.com\/bitovi\/status\/601082639991214080",
      "type_name": "tweet",
      "feed_name": "twitter",
      "body": null,
      "title": "RT @<a class=\"tweet-url username\" href=\"https:\/\/twitter.com\/uxmad\" rel=\"nofollow\">uxmad<\/a>: Happy to announce that Tom Greever @<a class=\"tweet-url username\" href=\"https:\/\/twitter.com\/tomgreever\" rel=\"nofollow\">tomgreever<\/a> will be speaking at <a class=\"tweet-url hashtag\" href=\"https:\/\/twitter.com\/#!\/search?q=%23MadPlusUX\" rel=\"nofollow\" title=\"#MadPlusUX\">#MadPlusUX<\/a> <a href=\"http:\/\/t.co\/33riBsrRJ1\" rel=\"nofollow\">http:\/\/t.co\/33riBsrRJ1<\/a>",
      "id": 3406
    },
    {
      "is_pinned": false,
      "is_approved": true,
      "service_ids": [
        57
      ],
      "author": {
        "avatar_url": "http:\/\/pbs.twimg.com\/profile_images\/445588675754090498\/nsGAtnRi_normal.png",
        "id": "bitovi"
      },
      "thread_updated_at": "2015-05-20T16:48:47.000Z",
      "thread_updated_ts": 1432140527,
      "updated_at": "2015-06-01T16:39:58.931Z",
      "created_at": "2015-06-01T16:39:58.931Z",
      "images": [],
      "url": "https:\/\/twitter.com\/bitovi\/status\/601067054993539072",
      "type_name": "tweet",
      "feed_name": "twitter",
      "body": null,
      "title": "RT @<a class=\"tweet-url username\" href=\"https:\/\/twitter.com\/m_mujica\" rel=\"nofollow\">m_mujica<\/a>: 1 year already since I joined @<a class=\"tweet-url username\" href=\"https:\/\/twitter.com\/bitovi\" rel=\"nofollow\">bitovi<\/a>, how cool is that? =)",
      "id": 3407
    },
    {
      "is_pinned": false,
      "is_approved": true,
      "service_ids": [
        57
      ],
      "author": {
        "avatar_url": "http:\/\/pbs.twimg.com\/profile_images\/445588675754090498\/nsGAtnRi_normal.png",
        "id": "bitovi"
      },
      "thread_updated_at": "2015-05-20T16:43:03.000Z",
      "thread_updated_ts": 1432140183,
      "updated_at": "2015-06-01T16:39:59.046Z",
      "created_at": "2015-06-01T16:39:59.046Z",
      "images": [],
      "url": "https:\/\/twitter.com\/bitovi\/status\/601065611888873472",
      "type_name": "tweet",
      "feed_name": "twitter",
      "body": null,
      "title": "We're covering the difference between the == and === operators in 20 min: <a href=\"https:\/\/t.co\/kgXKePOM57\" rel=\"nofollow\">https:\/\/t.co\/kgXKePOM57<\/a>",
      "id": 3408
    },
    {
      "is_pinned": false,
      "is_approved": true,
      "service_ids": [
        57
      ],
      "author": {
        "avatar_url": "http:\/\/pbs.twimg.com\/profile_images\/445588675754090498\/nsGAtnRi_normal.png",
        "id": "bitovi"
      },
      "thread_updated_at": "2015-05-15T06:13:45.000Z",
      "thread_updated_ts": 1431670425,
      "updated_at": "2015-06-01T16:39:59.154Z",
      "created_at": "2015-06-01T16:39:59.154Z",
      "images": [],
      "url": "https:\/\/twitter.com\/bitovi\/status\/599095302579036160",
      "type_name": "tweet",
      "feed_name": "twitter",
      "body": null,
      "title": "Training Series \u2013 Types, Operators and Primitives <a href=\"http:\/\/t.co\/EVo82ZIPue\" rel=\"nofollow\">http:\/\/t.co\/EVo82ZIPue<\/a> via @<a class=\"tweet-url username\" href=\"https:\/\/twitter.com\/bitovi\" rel=\"nofollow\">bitovi<\/a>",
      "id": 3409
    },
    {
      "is_pinned": false,
      "is_approved": true,
      "service_ids": [
        57
      ],
      "author": {
        "avatar_url": "http:\/\/pbs.twimg.com\/profile_images\/445588675754090498\/nsGAtnRi_normal.png",
        "id": "bitovi"
      },
      "thread_updated_at": "2015-05-15T06:11:53.000Z",
      "thread_updated_ts": 1431670313,
      "updated_at": "2015-06-01T16:39:59.260Z",
      "created_at": "2015-06-01T16:39:59.260Z",
      "images": [],
      "url": "https:\/\/twitter.com\/bitovi\/status\/599094833098153984",
      "type_name": "tweet",
      "feed_name": "twitter",
      "body": null,
      "title": "@<a class=\"tweet-url username\" href=\"https:\/\/twitter.com\/codylindley\" rel=\"nofollow\">codylindley<\/a> loved that article. Very thorough. Some veteran advice in there. FE engineering is a lot more than picking a framework.",
      "id": 3410
    },
    {
      "is_pinned": false,
      "is_approved": true,
      "service_ids": [
        57
      ],
      "author": {
        "avatar_url": "http:\/\/pbs.twimg.com\/profile_images\/445588675754090498\/nsGAtnRi_normal.png",
        "id": "bitovi"
      },
      "thread_updated_at": "2015-05-15T06:05:32.000Z",
      "thread_updated_ts": 1431669932,
      "updated_at": "2015-06-01T16:39:59.379Z",
      "created_at": "2015-06-01T16:39:59.379Z",
      "images": [],
      "url": "https:\/\/twitter.com\/bitovi\/status\/599093234661462016",
      "type_name": "tweet",
      "feed_name": "twitter",
      "body": null,
      "title": "@<a class=\"tweet-url username\" href=\"https:\/\/twitter.com\/bredeleca\" rel=\"nofollow\">bredeleca<\/a> awesome thanks for reading!",
      "id": 3411
    },
    {
      "is_pinned": false,
      "is_approved": true,
      "service_ids": [
        57
      ],
      "author": {
        "avatar_url": "http:\/\/pbs.twimg.com\/profile_images\/445588675754090498\/nsGAtnRi_normal.png",
        "id": "bitovi"
      },
      "thread_updated_at": "2015-05-14T22:06:13.000Z",
      "thread_updated_ts": 1431641173,
      "updated_at": "2015-06-01T16:39:59.501Z",
      "created_at": "2015-06-01T16:39:59.501Z",
      "images": [],
      "url": "https:\/\/twitter.com\/bitovi\/status\/598972611800862720",
      "type_name": "tweet",
      "feed_name": "twitter",
      "body": null,
      "title": "RT @<a class=\"tweet-url username\" href=\"https:\/\/twitter.com\/documentjs\" rel=\"nofollow\">documentjs<\/a>: Live Style Guides for Teams, Powered by DocumentJS\n<a href=\"http:\/\/t.co\/EVd32EdUYw\" rel=\"nofollow\">http:\/\/t.co\/EVd32EdUYw<\/a>",
      "id": 3412
    },
    {
      "is_pinned": false,
      "is_approved": true,
      "service_ids": [
        57
      ],
      "author": {
        "avatar_url": "http:\/\/pbs.twimg.com\/profile_images\/445588675754090498\/nsGAtnRi_normal.png",
        "id": "bitovi"
      },
      "thread_updated_at": "2015-05-14T05:04:32.000Z",
      "thread_updated_ts": 1431579872,
      "updated_at": "2015-06-01T16:39:59.618Z",
      "created_at": "2015-06-01T16:39:59.618Z",
      "images": [],
      "url": "https:\/\/twitter.com\/bitovi\/status\/598715494988947456",
      "type_name": "tweet",
      "feed_name": "twitter",
      "body": null,
      "title": "RT @<a class=\"tweet-url username\" href=\"https:\/\/twitter.com\/lezoudali\" rel=\"nofollow\">lezoudali<\/a>: Enjoying @<a class=\"tweet-url username\" href=\"https:\/\/twitter.com\/justinbmeyer\" rel=\"nofollow\">justinbmeyer<\/a> free weekly Javascript webcast.  you can watch the first webcast here &gt; <a href=\"http:\/\/t.co\/x6onOcwl70\" rel=\"nofollow\">http:\/\/t.co\/x6onOcwl70<\/a>",
      "id": 3413
    },
    {
      "is_pinned": false,
      "is_approved": true,
      "service_ids": [
        57
      ],
      "author": {
        "avatar_url": "http:\/\/pbs.twimg.com\/profile_images\/445588675754090498\/nsGAtnRi_normal.png",
        "id": "bitovi"
      },
      "thread_updated_at": "2015-05-14T02:01:34.000Z",
      "thread_updated_ts": 1431568894,
      "updated_at": "2015-06-01T16:39:59.724Z",
      "created_at": "2015-06-01T16:39:59.724Z",
      "images": [],
      "url": "https:\/\/twitter.com\/bitovi\/status\/598669452587085824",
      "type_name": "tweet",
      "feed_name": "twitter",
      "body": null,
      "title": "RT @<a class=\"tweet-url username\" href=\"https:\/\/twitter.com\/codylindley\" rel=\"nofollow\">codylindley<\/a>: I love seeing this \u201cJS Project Checklist \u201c from the @<a class=\"tweet-url username\" href=\"https:\/\/twitter.com\/bitovi\" rel=\"nofollow\">bitovi<\/a> guys. <a href=\"http:\/\/t.co\/jrCaYJHfcq\" rel=\"nofollow\">http:\/\/t.co\/jrCaYJHfcq<\/a> Reminds me of this: <a href=\"http:\/\/t.co\/V\" rel=\"nofollow\">http:\/\/t.co\/V<\/a>\u2026",
      "id": 3414
    },
    {
      "is_pinned": false,
      "is_approved": true,
      "service_ids": [
        57
      ],
      "author": {
        "avatar_url": "http:\/\/pbs.twimg.com\/profile_images\/445588675754090498\/nsGAtnRi_normal.png",
        "id": "bitovi"
      },
      "thread_updated_at": "2015-05-13T17:11:13.000Z",
      "thread_updated_ts": 1431537073,
      "updated_at": "2015-06-01T16:39:59.864Z",
      "created_at": "2015-06-01T16:39:59.864Z",
      "images": [],
      "url": "https:\/\/twitter.com\/bitovi\/status\/598535984695775233",
      "type_name": "tweet",
      "feed_name": "twitter",
      "body": null,
      "title": "RT @<a class=\"tweet-url username\" href=\"https:\/\/twitter.com\/alexisabril\" rel=\"nofollow\">alexisabril<\/a>: And we're live! Join us as we discuss how types and primitives work in memory! <a href=\"https:\/\/t.co\/J3QpaS4fhB\" rel=\"nofollow\">https:\/\/t.co\/J3QpaS4fhB<\/a> <a class=\"tweet-url hashtag\" href=\"https:\/\/twitter.com\/#!\/search?q=%23JavaScript\" rel=\"nofollow\" title=\"#JavaScript\">#JavaScript<\/a> <a class=\"tweet-url hashtag\" href=\"https:\/\/twitter.com\/#!\/search?q=%23traini\" rel=\"nofollow\" title=\"#traini\">#traini<\/a>\u2026",
      "id": 3415
    },
    {
      "is_pinned": false,
      "is_approved": true,
      "service_ids": [
        57
      ],
      "author": {
        "avatar_url": "http:\/\/pbs.twimg.com\/profile_images\/445588675754090498\/nsGAtnRi_normal.png",
        "id": "bitovi"
      },
      "thread_updated_at": "2015-05-13T17:00:16.000Z",
      "thread_updated_ts": 1431536416,
      "updated_at": "2015-06-01T16:39:59.981Z",
      "created_at": "2015-06-01T16:39:59.981Z",
      "images": [],
      "url": "https:\/\/twitter.com\/bitovi\/status\/598533228744544258",
      "type_name": "tweet",
      "feed_name": "twitter",
      "body": null,
      "title": "A JavaScript Project Checklist: Why You Need One, What's In Ours, and The Real Reasons Projects Fail... <a href=\"http:\/\/t.co\/yyDRGrNVuY\" rel=\"nofollow\">http:\/\/t.co\/yyDRGrNVuY<\/a>",
      "id": 3416
    },
    {
      "is_pinned": false,
      "is_approved": true,
      "service_ids": [
        57
      ],
      "author": {
        "avatar_url": "http:\/\/pbs.twimg.com\/profile_images\/445588675754090498\/nsGAtnRi_normal.png",
        "id": "bitovi"
      },
      "thread_updated_at": "2015-05-13T16:52:41.000Z",
      "thread_updated_ts": 1431535961,
      "updated_at": "2015-06-01T16:40:00.109Z",
      "created_at": "2015-06-01T16:40:00.109Z",
      "images": [],
      "url": "https:\/\/twitter.com\/bitovi\/status\/598531319912484864",
      "type_name": "tweet",
      "feed_name": "twitter",
      "body": null,
      "title": "A JavaScript Project Checklist: Why You Need One, What's In Ours, and The Real Reasons Projects Fail <a href=\"http:\/\/t.co\/ovrlFkqLmt\" rel=\"nofollow\">http:\/\/t.co\/ovrlFkqLmt<\/a> via @<a class=\"tweet-url username\" href=\"https:\/\/twitter.com\/bitovi\" rel=\"nofollow\">bitovi<\/a>",
      "id": 3417
    },
    {
      "is_pinned": false,
      "is_approved": true,
      "service_ids": [
        57
      ],
      "author": {
        "avatar_url": "http:\/\/pbs.twimg.com\/profile_images\/445588675754090498\/nsGAtnRi_normal.png",
        "id": "bitovi"
      },
      "thread_updated_at": "2015-05-13T16:29:01.000Z",
      "thread_updated_ts": 1431534541,
      "updated_at": "2015-06-01T16:40:00.224Z",
      "created_at": "2015-06-01T16:40:00.224Z",
      "images": [],
      "url": "https:\/\/twitter.com\/bitovi\/status\/598525365594689536",
      "type_name": "tweet",
      "feed_name": "twitter",
      "body": null,
      "title": "We'll be live soon with today's session: Types, Operators and Prims! <a href=\"https:\/\/t.co\/DSSnfUbJpi\" rel=\"nofollow\">https:\/\/t.co\/DSSnfUbJpi<\/a> Full sched: <a href=\"http:\/\/t.co\/pcju8p1fLd\" rel=\"nofollow\">http:\/\/t.co\/pcju8p1fLd<\/a> <a class=\"tweet-url hashtag\" href=\"https:\/\/twitter.com\/#!\/search?q=%23JavaScript\" rel=\"nofollow\" title=\"#JavaScript\">#JavaScript<\/a>",
      "id": 3418
    },
    {
      "is_pinned": false,
      "is_approved": true,
      "service_ids": [
        57
      ],
      "author": {
        "avatar_url": "http:\/\/pbs.twimg.com\/profile_images\/445588675754090498\/nsGAtnRi_normal.png",
        "id": "bitovi"
      },
      "thread_updated_at": "2015-05-11T15:11:29.000Z",
      "thread_updated_ts": 1431357089,
      "updated_at": "2015-06-01T16:40:00.412Z",
      "created_at": "2015-06-01T16:40:00.412Z",
      "images": [],
      "url": "https:\/\/twitter.com\/bitovi\/status\/597781075188842496",
      "type_name": "tweet",
      "feed_name": "twitter",
      "body": null,
      "title": "Our @<a class=\"tweet-url username\" href=\"https:\/\/twitter.com\/justinbmeyer\" rel=\"nofollow\">justinbmeyer<\/a> takes the stage at GOTO Chicago soon. <a href=\"http:\/\/t.co\/tjoPnA4G25\" rel=\"nofollow\">http:\/\/t.co\/tjoPnA4G25<\/a>",
      "id": 3419
    }
  ]
}
